MANIFEST.in
README.md
requirements.txt
setup.py
jabberwocky/__init__.py
jabberwocky/cli.py
jabberwocky/config.py
jabberwocky/core.py
jabberwocky/external_data.py
jabberwocky/openai_utils.py
jabberwocky/speech.py
jabberwocky/streaming.py
jabberwocky/utils.py
jabberwocky.egg-info/PKG-INFO
jabberwocky.egg-info/SOURCES.txt
jabberwocky.egg-info/dependency_links.txt
jabberwocky.egg-info/requires.txt
jabberwocky.egg-info/top_level.txt