Metadata-Version: 2.1
Name: jabberwocky
Version: 2.1.0
Summary: Core library powering a GUI providing an audio interface to GPT3.
Author: Harrison Mamin
Author-email: harrisonmamin@gmail.com
